my_package/__init__.py
my_package/utils.py
sample_texthelper-0.1.0.dist-info/METADATA
sample_texthelper-0.1.0.dist-info/WHEEL
sample_texthelper-0.1.0.dist-info/top_level.txt
sample_texthelper-0.1.0.dist-info/RECORD
