Metadata-Version: 2.1
Name: sample-texthelper
Version: 0.1.0
Summary: A sample Python app for text helper functions
Author: Sharath Shet
